Workbook

Sheet Sheet1
A1: Channel | B1: Spend | C1: Impressions | D1: Clicks | E1: Conversions | F1: Revenue | G1: CTR | H1: Conversion Rate | I1: CPC | J1: CAC | K1: ROAS
A2: Email | B2: 5000 | C2: 50000 | D2: 2500 | E2: 250 | F2: 25000 | G2: =D2/C2*100 -> 5 | H2: =E2/D2*100 -> 10 | I2: =B2/D2 -> 2 | J2: =B2/E2 -> 20 | K2: =F2/B2 -> 5
A3: Social Media | B3: 8000 | C3: 70000 | D3: 3500 | E3: 180 | F3: 22000 | G3: =D3/C3*100 -> 5 | H3: =E3/D3*100 -> 5.1428571 | I3: =B3/D3 -> 2.2857143 | J3: =B3/E3 -> 44.444444 | K3: =F3/B3 -> 2.75
A4: Paid Search | B4: 12000 | C4: 90000 | D4: 4000 | E4: 320 | F4: 45000 | G4: =D4/C4*100 -> 4.4444444 | H4: =E4/D4*100 -> 8 | I4: =B4/D4 -> 3 | J4: =B4/E4 -> 37.5 | K4: =F4/B4 -> 3.75
A5: Display Ads | B5: 6000 | C5: 60000 | D5: 2500 | E5: 120 | F5: 15000 | G5: =D5/C5*100 -> 4.1666667 | H5: =E5/D5*100 -> 4.8 | I5: =B5/D5 -> 2.4 | J5: =B5/E5 -> 50 | K5: =F5/B5 -> 2.5
A6: Email | B6: 4500 | C6: 48000 | D6: 2200 | E6: 230 | F6: 23000 | G6: =D6/C6*100 -> 4.5833333 | H6: =E6/D6*100 -> 10.454545 | I6: =B6/D6 -> 2.0454545 | J6: =B6/E6 -> 19.565217 | K6: =F6/B6 -> 5.1111111
A7: Social Media | B7: 7500 | C7: 65000 | D7: 3200 | E7: 170 | F7: 21000 | G7: =D7/C7*100 -> 4.9230769 | H7: =E7/D7*100 -> 5.3125 | I7: =B7/D7 -> 2.34375 | J7: =B7/E7 -> 44.117647 | K7: =F7/B7 -> 2.8
A8: Paid Search | B8: 13000 | C8: 95000 | D8: 4300 | E8: 340 | F8: 48000 | G8: =D8/C8*100 -> 4.5263158 | H8: =E8/D8*100 -> 7.9069767 | I8: =B8/D8 -> 3.0232558 | J8: =B8/E8 -> 38.235294 | K8: =F8/B8 -> 3.6923077
A9: Display Ads | B9: 5500 | C9: 58000 | D9: 2400 | E9: 110 | F9: 14000 | G9: =D9/C9*100 -> 4.137931 | H9: =E9/D9*100 -> 4.5833333 | I9: =B9/D9 -> 2.2916667 | J9: =B9/E9 -> 50 | K9: =F9/B9 -> 2.5454545

Sheet Summary
A1: Channel | B1: Total Spend | C1: Total Revenue | D1: Total Conversions | E1: ROAS | J1: Channel | K1: Revenue
A2: Email | B2: =SUMIF(Sheet1!A:A,"Email",Sheet1!B:B) -> 9500 | C2: =SUMIF(Sheet1!A:A,"Email",Sheet1!F:F) -> 48000 | D2: =SUMIF(Sheet1!A:A,"Email",Sheet1!E:E) -> 480 | E2: =C2/B2 -> 5.0526316 | J2: Email | K2: 48000
A3: Social Media | B3: =SUMIF(Sheet1!A:A,"Social Media",Sheet1!B:B) -> 15500 | C3: =SUMIF(Sheet1!A:A,"Social Media",Sheet1!F:F) -> 43000 | D3: =SUMIF(Sheet1!A:A,"Social Media",Sheet1!E:E) -> 350 | E3: =C3/B3 -> 2.7741935 | J3: Social Media | K3: 43000
A4: Paid Search | B4: =SUMIF(Sheet1!A:A,"Paid Search",Sheet1!B:B) -> 25000 | C4: =SUMIF(Sheet1!A:A,"Paid Search",Sheet1!F:F) -> 93000 | D4: =SUMIF(Sheet1!A:A,"Paid Search",Sheet1!E:E) -> 660 | E4: =C4/B4 -> 3.72 | J4: Paid Search | K4: 93000
A5: Display Ads | B5: =SUMIF(Sheet1!A:A,"Display Ads",Sheet1!B:B) -> 11500 | C5: =SUMIF(Sheet1!A:A,"Display Ads",Sheet1!F:F) -> 29000 | D5: =SUMIF(Sheet1!A:A,"Display Ads",Sheet1!E:E) -> 230 | E5: =C5/B5 -> 2.5217391 | J5: Display Ads | K5: 29000
J8: Channel | K8: ROAS
J9: Email | K9: 5.0526316
J10: Social Media | K10: 2.7741935
J11: Paid Search | K11: 3.72
J12: Display Ads | K12: 2.5217391
B20: 📊 Insight – Revenue by Channel
B21: Paid Search generates the highest revenue, showing strong high-intent customer acquisition. Email also performs efficiently with strong conversion-driven revenue.
B32: 📊 Insight – Spend vs Revenue
B33: Paid Search has the highest marketing spend but also delivers the highest revenue, showing a scale-driven but effective strategy. Email marketing achieves strong revenue with relatively lower spend, making it the most cost-efficient channel. Display Ads show low revenue compared to spend, indicating poor return on investment.
B44: 📊 Insight – ROAS by Channel
B45: Email marketing has the highest ROAS, making it the most efficient channel in terms of return on ad spend. Paid Search delivers moderate ROAS with strong revenue contribution. Social Media shows average efficiency, while Display Ads have the lowest ROAS, indicating inefficient budget utilization and need for optimization.
